vmware_reporter/__init__.py
vmware_reporter/__main__.py
vmware_reporter/_version.py
vmware_reporter/cluster.py
vmware_reporter/customvalue.py
vmware_reporter/datastore.py
vmware_reporter/export.py
vmware_reporter/host.py
vmware_reporter/inventory.py
vmware_reporter/net.py
vmware_reporter/perf.py
vmware_reporter/pool.py
vmware_reporter/report.py
vmware_reporter/settings.py
vmware_reporter/tag.py
vmware_reporter/vm.py
vmware_reporter-0.4.1.dist-info/LICENSE.txt
vmware_reporter-0.4.1.dist-info/METADATA
vmware_reporter-0.4.1.dist-info/WHEEL
vmware_reporter-0.4.1.dist-info/entry_points.txt
vmware_reporter-0.4.1.dist-info/top_level.txt
vmware_reporter-0.4.1.dist-info/RECORD
