Metadata-Version: 2.1
Name: vmware-reporter
Version: 0.4.1
Summary: Interact easily with your VMWare clusters.
Author-email: Sébastien Hocquet <dev@ipamo.net>
Project-URL: Homepage, https://github.com/ipamo/vmware-reporter
Project-URL: Bug Tracker, https://github.com/ipamo/vmware-reporter/issues
Keywords: vmware,vsphere,vm,reporter
Classifier: Development Status :: 4 - Beta
Classifier: License :: OSI Approved :: MIT License
Classifier: Operating System :: OS Independent
Classifier: Programming Language :: Python :: 3
Classifier: Environment :: Console
Classifier: Topic :: Software Development :: Libraries
Requires-Python: >=3.8
License-File: LICENSE.txt
Requires-Dist: zut[default]>=1.1.5
Requires-Dist: pyvmomi
Requires-Dist: requests
Provides-Extra: excel
Requires-Dist: zut[excel]>=0.9.4; extra == "excel"
Provides-Extra: smb
Requires-Dist: zut[smb]>=0.9.4; extra == "smb"
